{
  "updated_at": "2026-05-09T10:29:13.557336+08:00",
  "count": 57,
  "topics": [
    {
      "id": "b328a7a67cda",
      "title": "《国际税收》 朱青（税务433）",
      "summary": "2022年税务硕士考研群：830952137；\n2022年税务硕士考研群：830952137；\n2022年税务硕士考研群：830952137；\n2022年税务硕士考研群：830952137；\n2022年税务硕士考研群：830952137；",
      "source": "B站",
      "platform_class": "platform-bilibili",
      "author": "小熊老师带你飞",
      "url": "http://www.bilibili.com/video/av717134900",
      "time": "2026-05-09 10:29",
      "heat": 12325,
      "discussions": "565",
      "tags": [],
      "isHot": true,
      "detail": "<p>2022年税务硕士考研群：830952137；\n2022年税务硕士考研群：830952137；\n2022年税务硕士考研群：830952137；\n2022年税务硕士考研群：830952137；\n2022年税务硕士考研群：830952137；</p>"
    },
    {
      "id": "8da0db090837",
      "title": "🔥网上办理税务登记全流程",
      "summary": "拿到营业执照后足不出户就可以网上办理税务登记啦！",
      "source": "B站",
      "platform_class": "platform-bilibili",
      "author": "跟着可可学实操",
      "url": "http://www.bilibili.com/video/av704446276",
      "time": "2026-05-09 10:29",
      "heat": 7545,
      "discussions": "253",
      "tags": [],
      "isHot": true,
      "detail": "<p>拿到营业执照后足不出户就可以网上办理税务登记啦！</p>"
    },
    {
      "id": "85fb3d48699e",
      "title": "新版电子税务局，小规模零申报操作流程",
      "summary": "-",
      "source": "B站",
      "platform_class": "platform-bilibili",
      "author": "百合财税",
      "url": "http://www.bilibili.com/video/av1456007058",
      "time": "2026-05-09 10:29",
      "heat": 7455,
      "discussions": "218",
      "tags": [],
      "isHot": true,
      "detail": "<p>-</p>"
    },
    {
      "id": "5e20f4c1d8eb",
      "title": "海淘邮件显示什么才可能被税？？海关真就那么可怕！其实个人清关真的很简单！海关绝不是洪水猛兽！交税是我们应尽的义务哟！！",
      "summary": "海淘邮件显示什么才可能被税？？海关真就那么可怕！其实个人清关真的很简单！海关绝不是洪水猛兽！交税是我们应尽的义务哟！！",
      "source": "B站",
      "platform_class": "platform-bilibili",
      "author": "玩塑料小人的闯关族",
      "url": "http://www.bilibili.com/video/av333294282",
      "time": "2026-05-09 10:29",
      "heat": 5119,
      "discussions": "233",
      "tags": [],
      "isHot": false,
      "detail": "<p>海淘邮件显示什么才可能被税？？海关真就那么可怕！其实个人清关真的很简单！海关绝不是洪水猛兽！交税是我们应尽的义务哟！！</p>"
    },
    {
      "id": "8257b0b35fb4",
      "title": "2025年新版电子税务局税务注销全流程",
      "summary": "-",
      "source": "B站",
      "platform_class": "platform-bilibili",
      "author": "晗妈会计",
      "url": "http://www.bilibili.com/video/av114640730195595",
      "time": "2026-05-09 10:29",
      "heat": 3280,
      "discussions": "125",
      "tags": [],
      "isHot": false,
      "detail": "<p>-</p>"
    },
    {
      "id": "dbb9b7c2f835",
      "title": "【史诗级提分干货】全网最好理解的国际税收框架——大白话的国际税收||433||国际税收||税务专硕||经验||方法||",
      "summary": "【史诗级提分干货】全网最好理解的国际税收框架——大白话的国际税收||433||国际税收||税务专硕||经验||方法||",
      "source": "B站",
      "platform_class": "platform-bilibili",
      "author": "映山学长税务专硕433",
      "url": "http://www.bilibili.com/video/av322096277",
      "time": "2026-05-09 10:29",
      "heat": 3244,
      "discussions": "23",
      "tags": [],
      "isHot": false,
      "detail": "<p>【史诗级提分干货】全网最好理解的国际税收框架——大白话的国际税收||433||国际税收||税务专硕||经验||方法||</p>"
    },
    {
      "id": "c9dfa4ebbaa9",
      "title": "2025年最新工商年报的详细申报流程！",
      "summary": "2025年最新工商年报的详细申报流程！",
      "source": "B站",
      "platform_class": "platform-bilibili",
      "author": "小财分享师",
      "url": "http://www.bilibili.com/video/av113979204571119",
      "time": "2026-05-09 10:29",
      "heat": 3039,
      "discussions": "57",
      "tags": [],
      "isHot": false,
      "detail": "<p>2025年最新工商年报的详细申报流程！</p>"
    },
    {
      "id": "ff92b107385a",
      "title": "【会计实操】纳税申报 | 业务10 申报上月增值税及附加 （科云杯）",
      "summary": "本视频为科云杯会计技能实操讲解7月8日业务10增值税纳税申报\n\n增值税纳税申报表包括以下几个： 《增值税纳税申报表（一般纳税人适用）》 《增值税纳税申报表附列资料（一）》（本期销售情况明细） 《增值税纳税申报表附列资料（二）》（本期进项税额明细） 《增值税纳税申报表附列资料（三）》（服务、不动产和无形资产扣除项目 明细）填写说明 《增值税纳税申报表附列资料（四）》（税额抵减情况表） 《增值税纳税申",
      "source": "B站",
      "platform_class": "platform-bilibili",
      "author": "misyusensei",
      "url": "http://www.bilibili.com/video/av113283705149914",
      "time": "2026-05-09 10:29",
      "heat": 2899,
      "discussions": "22",
      "tags": [],
      "isHot": false,
      "detail": "<p>本视频为科云杯会计技能实操讲解7月8日业务10增值税纳税申报\n\n增值税纳税申报表包括以下几个： 《增值税纳税申报表（一般纳税人适用）》 《增值税纳税申报表附列资料（一）》（本期销售情况明细） 《增值税纳税申报表附列资料（二）》（本期进项税额明细） 《增值税纳税申报表附列资料（三）》（服务、不动产和无形资产扣除项目 明细）填写说明 《增值税纳税申报表附列资料（四）》（税额抵减情况表） 《增值税纳税申</p>"
    },
    {
      "id": "f6192add8402",
      "title": "工信部新车申报公示查询方法，手机端同理",
      "summary": "工信部汽车申报公示如何查询？（以第378批为例，吉利翼真MPV、极氪007性能版）",
      "source": "B站",
      "platform_class": "platform-bilibili",
      "author": "若只如初见iwl",
      "url": "http://www.bilibili.com/video/av792088287",
      "time": "2026-05-09 10:29",
      "heat": 2192,
      "discussions": "13",
      "tags": [],
      "isHot": false,
      "detail": "<p>工信部汽车申报公示如何查询？（以第378批为例，吉利翼真MPV、极氪007性能版）</p>"
    },
    {
      "id": "953760b7f9a5",
      "title": "电商平台政策解读及增值税申报详细流程",
      "summary": "-",
      "source": "B站",
      "platform_class": "platform-bilibili",
      "author": "晗妈会计",
      "url": "http://www.bilibili.com/video/av115349114586330",
      "time": "2026-05-09 10:29",
      "heat": 1787,
      "discussions": "29",
      "tags": [],
      "isHot": false,
      "detail": "<p>-</p>"
    },
    {
      "id": "c383d1e826af",
      "title": "广东省契税电子申报教程",
      "summary": "广东省契税电子申报教程，粤税通",
      "source": "B站",
      "platform_class": "platform-bilibili",
      "author": "__Mr_H",
      "url": "http://www.bilibili.com/video/av887997978",
      "time": "2026-05-09 10:29",
      "heat": 1763,
      "discussions": "6",
      "tags": [],
      "isHot": false,
      "detail": "<p>广东省契税电子申报教程，粤税通</p>"
    },
    {
      "id": "9c04941ec2ce",
      "title": "财务Python与RPA机器人应用案例详解|自动申报个税",
      "summary": "财务Python与RPA机器人应用案例详解|自动申报个税",
      "source": "B站",
      "platform_class": "platform-bilibili",
      "author": "徐猴猴财务编程",
      "url": "http://www.bilibili.com/video/av508797376",
      "time": "2026-05-09 10:29",
      "heat": 1615,
      "discussions": "23",
      "tags": [],
      "isHot": false,
      "detail": "<p>财务Python与RPA机器人应用案例详解|自动申报个税</p>"
    },
    {
      "id": "f02d9edab46c",
      "title": "个税汇算清缴集中申报操作流程",
      "summary": "个税汇算清缴集中申报操作流程",
      "source": "B站",
      "platform_class": "platform-bilibili",
      "author": "芈燮",
      "url": "http://www.bilibili.com/video/av757245912",
      "time": "2026-05-09 10:29",
      "heat": 1381,
      "discussions": "2",
      "tags": [],
      "isHot": false,
      "detail": "<p>个税汇算清缴集中申报操作流程</p>"
    },
    {
      "id": "379d196d6cca",
      "title": "V3.8酒类消费税及附加税费网上申报教学版案例02-wal-20211229",
      "summary": "V3.8酒类消费税及附加税费网上申报教学版案例02-wal-20211229",
      "source": "B站",
      "platform_class": "platform-bilibili",
      "author": "风冰心可",
      "url": "http://www.bilibili.com/video/av520424644",
      "time": "2026-05-09 10:29",
      "heat": 1260,
      "discussions": "13",
      "tags": [],
      "isHot": false,
      "detail": "<p>V3.8酒类消费税及附加税费网上申报教学版案例02-wal-20211229</p>"
    },
    {
      "id": "b948d5ffe64b",
      "title": "一般纳税人增值税申报讲解",
      "summary": "-",
      "source": "B站",
      "platform_class": "platform-bilibili",
      "author": "李岩讲财税",
      "url": "http://www.bilibili.com/video/av115852296852170",
      "time": "2026-05-09 10:29",
      "heat": 1192,
      "discussions": "14",
      "tags": [],
      "isHot": false,
      "detail": "<p>-</p>"
    },
    {
      "id": "399332c051f8",
      "title": "PropFirm 收入与税务申报",
      "summary": "下半年很多人都遇到的补税情况，了解清楚，不罚款。",
      "source": "B站",
      "platform_class": "platform-bilibili",
      "author": "昵称被注册的-小水果",
      "url": "http://www.bilibili.com/video/av115705143889829",
      "time": "2026-05-09 10:29",
      "heat": 1071,
      "discussions": "111",
      "tags": [],
      "isHot": false,
      "detail": "<p>下半年很多人都遇到的补税情况，了解清楚，不罚款。</p>"
    },
    {
      "id": "e3036e911caf",
      "title": "十里洋场丨响遍民国的《申报》已停刊，但是申报馆已然存在",
      "summary": "1840年代上海租界开辟之后\n租界当局在现在上海市中心\n辟筑了6条东西方向的马路\n\n中国人习惯性地以1-6称呼这6条马路\n大马路是南京路；二马路是九江路\n三马路是汉口路；四马路是福州路\n五马路是广东路；六马路是北海路\n这6条马路可谓各有各的特色\n其中三马路汉口路最著名的就是报馆林立\n\n汉口路山东路口曾是上海报馆集中地\n1910年开始有报纸选择在这里设馆办报\n最高峰时这里有数十家报社同时办公\n每天清",
      "source": "B站",
      "platform_class": "platform-bilibili",
      "author": "城考君",
      "url": "http://www.bilibili.com/video/av523715448",
      "time": "2026-05-09 10:29",
      "heat": 985,
      "discussions": "19",
      "tags": [],
      "isHot": false,
      "detail": "<p>1840年代上海租界开辟之后\n租界当局在现在上海市中心\n辟筑了6条东西方向的马路\n\n中国人习惯性地以1-6称呼这6条马路\n大马路是南京路；二马路是九江路\n三马路是汉口路；四马路是福州路\n五马路是广东路；六马路是北海路\n这6条马路可谓各有各的特色\n其中三马路汉口路最著名的就是报馆林立\n\n汉口路山东路口曾是上海报馆集中地\n1910年开始有报纸选择在这里设馆办报\n最高峰时这里有数十家报社同时办公\n每天清</p>"
    },
    {
      "id": "b3330fdc3337",
      "title": "「影刀RPA」 财务机器人：税务局自动纳税申报",
      "summary": "如需在企业里使用该自动化应用，填写申请：https://ying-dao.feishu.cn/share/base/form/shrcnhAcnPkKTixfcWiVjqQ2uFh\n加入RPA学习群：https://mp.weixin.qq.com/s/5BLHkJq6Tk4Z-XxLtsjXOw",
      "source": "B站",
      "platform_class": "platform-bilibili",
      "author": "影刀RPA",
      "url": "http://www.bilibili.com/video/av647824949",
      "time": "2026-05-09 10:29",
      "heat": 946,
      "discussions": "14",
      "tags": [],
      "isHot": false,
      "detail": "<p>如需在企业里使用该自动化应用，填写申请：https://ying-dao.feishu.cn/share/base/form/shrcnhAcnPkKTixfcWiVjqQ2uFh\n加入RPA学习群：https://mp.weixin.qq.com/s/5BLHkJq6Tk4Z-XxLtsjXOw</p>"
    },
    {
      "id": "dbb8d368965a",
      "title": "4-3异地预缴|跨区域涉税事项全流程全全全～",
      "summary": "增值税及附加税预缴:\n1.登录项目所在地电子税务局;\n2.点“特定主体”选择“跨区域报验户”身份登陆;\n3.点对应要预缴的外经证[进入];\n4.守页点“我要办税”→“税费申报及缴纳”→“增值税及附加税费预缴申报”;\n5.税款所属期选“开票当月”→点“修改”填入对应的销售额(价税合计数)【确定]后增值税及附加税自动带出，核对数据是否正确，核对无误点[提交]→去缴款\n\n预缴企业所得税:\n点“我要办税”",
      "source": "B站",
      "platform_class": "platform-bilibili",
      "author": "财务方",
      "url": "http://www.bilibili.com/video/av113761738293815",
      "time": "2026-05-09 10:29",
      "heat": 922,
      "discussions": "18",
      "tags": [],
      "isHot": false,
      "detail": "<p>增值税及附加税预缴:\n1.登录项目所在地电子税务局;\n2.点“特定主体”选择“跨区域报验户”身份登陆;\n3.点对应要预缴的外经证[进入];\n4.守页点“我要办税”→“税费申报及缴纳”→“增值税及附加税费预缴申报”;\n5.税款所属期选“开票当月”→点“修改”填入对应的销售额(价税合计数)【确定]后增值税及附加税自动带出，核对数据是否正确，核对无误点[提交]→去缴款\n\n预缴企业所得税:\n点“我要办税”</p>"
    },
    {
      "id": "18a8a0b148d2",
      "title": "印花税申报操作流程",
      "summary": "印花税申报操作流程",
      "source": "B站",
      "platform_class": "platform-bilibili",
      "author": "会计收徒丶信德",
      "url": "http://www.bilibili.com/video/av115818205615535",
      "time": "2026-05-09 10:29",
      "heat": 900,
      "discussions": "14",
      "tags": [],
      "isHot": false,
      "detail": "<p>印花税申报操作流程</p>"
    },
    {
      "id": "eb8411c3962b",
      "title": "境外投资个税指南：如何避免20%资本利得税 | CRS | 个人所得税 | QDII | 港股通 |030",
      "summary": "国内对境外资本利得的20%税收监管已进入全面执行阶段，CRS和金税四期让海外账户的个人所得税无处遁形。普通投资者应通过合规渠道（如港股通、QDII）和主动申报个税降低税务风险。在监管与技术双轮驱动下，合规是唯一出路，忽视规则将导致高昂代价。\n目前A股的买卖差价所得暂免征收个人所得税，但股息红利所得根据持股期限适用差异化税率“0%-20% (按持股期)”。为当前最具税收优势的投资渠道，但前提是您认为",
      "source": "B站",
      "platform_class": "platform-bilibili",
      "author": "呆萌财",
      "url": "http://www.bilibili.com/video/av115910933221499",
      "time": "2026-05-09 10:29",
      "heat": 866,
      "discussions": "34",
      "tags": [],
      "isHot": false,
      "detail": "<p>国内对境外资本利得的20%税收监管已进入全面执行阶段，CRS和金税四期让海外账户的个人所得税无处遁形。普通投资者应通过合规渠道（如港股通、QDII）和主动申报个税降低税务风险。在监管与技术双轮驱动下，合规是唯一出路，忽视规则将导致高昂代价。\n目前A股的买卖差价所得暂免征收个人所得税，但股息红利所得根据持股期限适用差异化税率“0%-20% (按持股期)”。为当前最具税收优势的投资渠道，但前提是您认为</p>"
    },
    {
      "id": "8b7c10c94bdf",
      "title": "跨境电商要交税？！申报和缴纳是两回事！",
      "summary": "跨境电商要交税？！申报和缴纳是两回事！",
      "source": "B站",
      "platform_class": "platform-bilibili",
      "author": "远郊区打工人",
      "url": "http://www.bilibili.com/video/av114807143468986",
      "time": "2026-05-09 10:29",
      "heat": 730,
      "discussions": "19",
      "tags": [],
      "isHot": false,
      "detail": "<p>跨境电商要交税？！申报和缴纳是两回事！</p>"
    },
    {
      "id": "0ee80f9daead",
      "title": "出口退税备案详细流程来了",
      "summary": "-",
      "source": "B站",
      "platform_class": "platform-bilibili",
      "author": "晗妈会计",
      "url": "http://www.bilibili.com/video/av114973036514165",
      "time": "2026-05-09 10:29",
      "heat": 551,
      "discussions": "6",
      "tags": [],
      "isHot": false,
      "detail": "<p>-</p>"
    },
    {
      "id": "a57107d3688b",
      "title": "印花税申报",
      "summary": "印花税申报",
      "source": "B站",
      "platform_class": "platform-bilibili",
      "author": "Yoki朝朝呐",
      "url": "http://www.bilibili.com/video/av112941986744440",
      "time": "2026-05-09 10:29",
      "heat": 522,
      "discussions": "0",
      "tags": [],
      "isHot": false,
      "detail": "<p>印花税申报</p>"
    },
    {
      "id": "5e6e60953b00",
      "title": "取得境外所得如何通过个税APP申报个人所得税(浙江税务)",
      "summary": "宝子们！5月29日还没报境外所得个税的注意啦！今年起用个税APP就能搞定，超省心～\n\n哪些算境外所得？像海外工资、境外股息、转让境外房产等9类收入都要报，具体看财政部2020年3号公告！记得每年3月1日-6月30日申报，现在只剩最后几天，别漏了！\n\n操作超简单：打开个税APP，首页搜“年度汇算（取得境外所得适用）”，填境内外综合所得、经营所得，利息股息等分类所得单独填；境外已缴税别慌，系统自动算抵",
      "source": "B站",
      "platform_class": "platform-bilibili",
      "author": "税务师木木",
      "url": "http://www.bilibili.com/video/av114588066516202",
      "time": "2026-05-09 10:29",
      "heat": 472,
      "discussions": "3",
      "tags": [],
      "isHot": false,
      "detail": "<p>宝子们！5月29日还没报境外所得个税的注意啦！今年起用个税APP就能搞定，超省心～\n\n哪些算境外所得？像海外工资、境外股息、转让境外房产等9类收入都要报，具体看财政部2020年3号公告！记得每年3月1日-6月30日申报，现在只剩最后几天，别漏了！\n\n操作超简单：打开个税APP，首页搜“年度汇算（取得境外所得适用）”，填境内外综合所得、经营所得，利息股息等分类所得单独填；境外已缴税别慌，系统自动算抵</p>"
    },
    {
      "id": "7d2e83f0c517",
      "title": "会计实操丨旅客运输服务进项抵扣计算和申报丨零基础学会计",
      "summary": "-",
      "source": "B站",
      "platform_class": "platform-bilibili",
      "author": "橙子财税鸭",
      "url": "http://www.bilibili.com/video/av855312223",
      "time": "2026-05-09 10:29",
      "heat": 469,
      "discussions": "12",
      "tags": [],
      "isHot": false,
      "detail": "<p>-</p>"
    },
    {
      "id": "6262d427a0f0",
      "title": "超详细攻略！四分钟精讲跨区域涉税事项报告操作指引#建筑行业#跨区域涉税事项#电子税务局#会计",
      "summary": "超详细攻略！四分钟精讲跨区域涉税事项报告操作指引#建筑行业#跨区域涉税事项#电子税务局#会计",
      "source": "B站",
      "platform_class": "platform-bilibili",
      "author": "企巴兔财税",
      "url": "http://www.bilibili.com/video/av113588496762554",
      "time": "2026-05-09 10:29",
      "heat": 467,
      "discussions": "9",
      "tags": [],
      "isHot": false,
      "detail": "<p>超详细攻略！四分钟精讲跨区域涉税事项报告操作指引#建筑行业#跨区域涉税事项#电子税务局#会计</p>"
    },
    {
      "id": "c19b889387d0",
      "title": "定期定额个体户如何申报？",
      "summary": "-",
      "source": "B站",
      "platform_class": "platform-bilibili",
      "author": "利西说财税",
      "url": "http://www.bilibili.com/video/av114788084618847",
      "time": "2026-05-09 10:29",
      "heat": 454,
      "discussions": "13",
      "tags": [],
      "isHot": false,
      "detail": "<p>-</p>"
    },
    {
      "id": "e1fef66ee54f",
      "title": "“走出去”企业常见境外税收涉税风险及防范",
      "summary": "“走出去”企业常见境外税收涉税风险及防范",
      "source": "B站",
      "platform_class": "platform-bilibili",
      "author": "会计学习吧",
      "url": "http://www.bilibili.com/video/av113221059021266",
      "time": "2026-05-09 10:29",
      "heat": 450,
      "discussions": "2",
      "tags": [],
      "isHot": false,
      "detail": "<p>“走出去”企业常见境外税收涉税风险及防范</p>"
    },
    {
      "id": "4a4f9e989850",
      "title": "官方【工信部视频讲解-专精特新小巨人申报政策解读】",
      "summary": "官方\n来源与官方",
      "source": "B站",
      "platform_class": "platform-bilibili",
      "author": "复制搬运工",
      "url": "http://www.bilibili.com/video/av1903685578",
      "time": "2026-05-09 10:29",
      "heat": 379,
      "discussions": "8",
      "tags": [],
      "isHot": false,
      "detail": "<p>官方\n来源与官方</p>"
    },
    {
      "id": "aa8ff6c3d6c6",
      "title": "受益所有人信息如何申报",
      "summary": "-",
      "source": "B站",
      "platform_class": "platform-bilibili",
      "author": "凡小赛说财税",
      "url": "http://www.bilibili.com/video/av115008302220367",
      "time": "2026-05-09 10:29",
      "heat": 345,
      "discussions": "6",
      "tags": [],
      "isHot": false,
      "detail": "<p>-</p>"
    },
    {
      "id": "13c8d12ddd95",
      "title": "第十章（四）：来料加工贸易业务流程与税务申报",
      "summary": "第十章（四）：来料加工贸易业务流程与税务申报",
      "source": "B站",
      "platform_class": "platform-bilibili",
      "author": "雨暹",
      "url": "http://www.bilibili.com/video/av446014909",
      "time": "2026-05-09 10:29",
      "heat": 268,
      "discussions": "1",
      "tags": [],
      "isHot": false,
      "detail": "<p>第十章（四）：来料加工贸易业务流程与税务申报</p>"
    },
    {
      "id": "848c6ee8b6ea",
      "title": "关联交易申报及同期资料准备",
      "summary": "对关联交易申报和同期资料准备的相关业务知识进行讲解，可以帮助企业更好的判定企业双方的关联关系，提高申报数据的准确性，同时对同期资料的构成和各类文档的准备条件做了详细讲解，以此帮助企业熟悉关联交易申报，提高申报质量，降低企业涉税风险，助力企业发展。",
      "source": "B站",
      "platform_class": "platform-bilibili",
      "author": "财税郭同学-",
      "url": "http://www.bilibili.com/video/av811218170",
      "time": "2026-05-09 10:29",
      "heat": 266,
      "discussions": "1",
      "tags": [],
      "isHot": false,
      "detail": "<p>对关联交易申报和同期资料准备的相关业务知识进行讲解，可以帮助企业更好的判定企业双方的关联关系，提高申报数据的准确性，同时对同期资料的构成和各类文档的准备条件做了详细讲解，以此帮助企业熟悉关联交易申报，提高申报质量，降低企业涉税风险，助力企业发展。</p>"
    },
    {
      "id": "9b3b3b0c0e78",
      "title": "CRS: 2026 境外投資稅務申報教學：AI 自動計算美股/港股投資所得，個人所得稅 APP 報稅全攻略",
      "summary": "💡 境外投資報稅太複雜？請會計太貴？本視頻手把手教你使用最新的 AI 稅務工具，自動化處理你的券商月報表、年報表，一鍵生成符合審計要求的 Excel 底稿，讓你在個人所得稅 APP 申報時輕鬆無憂！\n\n📌 視頻核心內容：\n00:00 工具背景與核心價值（省時、省錢、防風險）\n01:08 免費體驗額度獲取與定價方案\n02:00 邀請碼機制：雙方均可獲得 50% 額外額度\n02:40 數據安全保障：本",
      "source": "B站",
      "platform_class": "platform-bilibili",
      "author": "财富种植园",
      "url": "http://www.bilibili.com/video/av116132493133650",
      "time": "2026-05-09 10:29",
      "heat": 241,
      "discussions": "14",
      "tags": [],
      "isHot": false,
      "detail": "<p>💡 境外投資報稅太複雜？請會計太貴？本視頻手把手教你使用最新的 AI 稅務工具，自動化處理你的券商月報表、年報表，一鍵生成符合審計要求的 Excel 底稿，讓你在個人所得稅 APP 申報時輕鬆無憂！\n\n📌 視頻核心內容：\n00:00 工具背景與核心價值（省時、省錢、防風險）\n01:08 免費體驗額度獲取與定價方案\n02:00 邀請碼機制：雙方均可獲得 50% 額外額度\n02:40 數據安全保障：本</p>"
    },
    {
      "id": "6f52948d7a53",
      "title": "【完全搞懂VAT！】欧洲跨境必修课：注册+申报+缴税，一次讲透！连平台代缴功能都教你怎么用！新卖家也能看懂",
      "summary": "这期视频我会用3分钟的结构，带你快速搞懂VAT注册 + 申报 + 缴税的核心流程，\n还会告诉你哪些平台支持免费代缴，怎么操作最省心，一看就懂，少走很多弯路。\n\n✅ 视频对应图文文章：\nhttps://mp.weixin.qq.com/s/Pl0U1pQcJoc5Fs8C4sQZ2Q",
      "source": "B站",
      "platform_class": "platform-bilibili",
      "author": "136F跨境小贴士",
      "url": "http://www.bilibili.com/video/av115434762469798",
      "time": "2026-05-09 10:29",
      "heat": 230,
      "discussions": "6",
      "tags": [],
      "isHot": false,
      "detail": "<p>这期视频我会用3分钟的结构，带你快速搞懂VAT注册 + 申报 + 缴税的核心流程，\n还会告诉你哪些平台支持免费代缴，怎么操作最省心，一看就懂，少走很多弯路。\n\n✅ 视频对应图文文章：\nhttps://mp.weixin.qq.com/s/Pl0U1pQcJoc5Fs8C4sQZ2Q</p>"
    },
    {
      "id": "451123192a7f",
      "title": "11 如何填写境外所得个税申报表（上）【个税年度汇算专题】",
      "summary": "深圳税务局",
      "source": "B站",
      "platform_class": "platform-bilibili",
      "author": "自然人税与法研究室",
      "url": "http://www.bilibili.com/video/av840066291",
      "time": "2026-05-09 10:29",
      "heat": 226,
      "discussions": "3",
      "tags": [],
      "isHot": false,
      "detail": "<p>深圳税务局</p>"
    },
    {
      "id": "69e9fed73f1d",
      "title": "抖店涉税申报数据如何核对",
      "summary": "抖店涉税申报数据如何核对",
      "source": "B站",
      "platform_class": "platform-bilibili",
      "author": "电商财务许哈哈",
      "url": "http://www.bilibili.com/video/av115406006132638",
      "time": "2026-05-09 10:29",
      "heat": 218,
      "discussions": "6",
      "tags": [],
      "isHot": false,
      "detail": "<p>抖店涉税申报数据如何核对</p>"
    },
    {
      "id": "6e513e4cfca7",
      "title": "新电子税务局外经证跨区域涉税事项报验管理",
      "summary": "-",
      "source": "B站",
      "platform_class": "platform-bilibili",
      "author": "平禾财会说",
      "url": "http://www.bilibili.com/video/av115744301974169",
      "time": "2026-05-09 10:29",
      "heat": 210,
      "discussions": "1",
      "tags": [],
      "isHot": false,
      "detail": "<p>-</p>"
    },
    {
      "id": "c0123dc6b505",
      "title": "分公司都需要申报哪些税零申报全流程",
      "summary": "-",
      "source": "B站",
      "platform_class": "platform-bilibili",
      "author": "晗妈会计",
      "url": "http://www.bilibili.com/video/av114822914050754",
      "time": "2026-05-09 10:29",
      "heat": 177,
      "discussions": "1",
      "tags": [],
      "isHot": false,
      "detail": "<p>-</p>"
    },
    {
      "id": "112674f31c75",
      "title": "精讲CRS系列03：CRS完整的交换流程及税务应对",
      "summary": "精讲CRS系列03：CRS完整的交换流程及税务应对",
      "source": "B站",
      "platform_class": "platform-bilibili",
      "author": "红茶女士Blacktea",
      "url": "http://www.bilibili.com/video/av116508436993303",
      "time": "2026-05-09 10:29",
      "heat": 155,
      "discussions": "1",
      "tags": [],
      "isHot": false,
      "detail": "<p>精讲CRS系列03：CRS完整的交换流程及税务应对</p>"
    },
    {
      "id": "4fc2720ec972",
      "title": "韩国电子入境申报全流程，到达前三天内在线填写电子申报，落地后便不再需要填写纸质申报表直接入境。#实用小技巧 #韩国旅游 #旅游攻略 #韩国电子入境申报",
      "summary": "-",
      "source": "B站",
      "platform_class": "platform-bilibili",
      "author": "随便中的随便ss",
      "url": "http://www.bilibili.com/video/av115625317957914",
      "time": "2026-05-09 10:29",
      "heat": 150,
      "discussions": "2",
      "tags": [],
      "isHot": false,
      "detail": "<p>-</p>"
    },
    {
      "id": "7c9746ad4080",
      "title": "31、干货分享之申报企业税务申报",
      "summary": "31、干货分享之申报企业税务申报",
      "source": "B站",
      "platform_class": "platform-bilibili",
      "author": "努力成为蛋总s",
      "url": "http://www.bilibili.com/video/av115625368296329",
      "time": "2026-05-09 10:29",
      "heat": 110,
      "discussions": "5",
      "tags": [],
      "isHot": false,
      "detail": "<p>31、干货分享之申报企业税务申报</p>"
    },
    {
      "id": "cfee548b0705",
      "title": "CRS：知识篇-非CRS国家大公开",
      "summary": "传说中的富豪克星 CRS 到底是什么？\n它到底怎么执行的让全世界的富豪唯恐不及？\nCRS对海外房地产的影响真的很大吗?\n有哪些国家加入这个制度来避免洗钱问题？\n又有哪些国家在没有CRS的前提下被称为避税天堂呢？\n快看影片来了解吧！\n-\n影片内容：\n0:06 CRS是什么？\n0:23 包含了哪些又不包含哪些？\n1:08 非CRS国家举例\n1:29 非CRS国选哪个好？\n-\n看完之后是否有更了解CRS",
      "source": "B站",
      "platform_class": "platform-bilibili",
      "author": "環球管家",
      "url": "http://www.bilibili.com/video/av82565539",
      "time": "2026-05-09 10:29",
      "heat": 109,
      "discussions": "1",
      "tags": [],
      "isHot": false,
      "detail": "<p>传说中的富豪克星 CRS 到底是什么？\n它到底怎么执行的让全世界的富豪唯恐不及？\nCRS对海外房地产的影响真的很大吗?\n有哪些国家加入这个制度来避免洗钱问题？\n又有哪些国家在没有CRS的前提下被称为避税天堂呢？\n快看影片来了解吧！\n-\n影片内容：\n0:06 CRS是什么？\n0:23 包含了哪些又不包含哪些？\n1:08 非CRS国家举例\n1:29 非CRS国选哪个好？\n-\n看完之后是否有更了解CRS</p>"
    },
    {
      "id": "27c303854ebd",
      "title": "双定个体户如何填写申报表？",
      "summary": "-",
      "source": "B站",
      "platform_class": "platform-bilibili",
      "author": "馒头娘说税",
      "url": "http://www.bilibili.com/video/av113077311766928",
      "time": "2026-05-09 10:29",
      "heat": 107,
      "discussions": "0",
      "tags": [],
      "isHot": false,
      "detail": "<p>-</p>"
    },
    {
      "id": "41e9712adacf",
      "title": "2025年境外收入在国内缴税的方法",
      "summary": "2025年境外收入在国内缴税的方法",
      "source": "B站",
      "platform_class": "platform-bilibili",
      "author": "淡定的飞马",
      "url": "http://www.bilibili.com/video/av116228072934922",
      "time": "2026-05-09 10:29",
      "heat": 91,
      "discussions": "6",
      "tags": [],
      "isHot": false,
      "detail": "<p>2025年境外收入在国内缴税的方法</p>"
    },
    {
      "id": "60ae07064567",
      "title": "划重点！干货分享：经营者集中申报标准的调整及其影响",
      "summary": "划重点！干货分享：经营者集中申报标准的调整及其影响",
      "source": "B站",
      "platform_class": "platform-bilibili",
      "author": "君合律师事务所",
      "url": "http://www.bilibili.com/video/av1700497445",
      "time": "2026-05-09 10:29",
      "heat": 87,
      "discussions": "0",
      "tags": [],
      "isHot": false,
      "detail": "<p>划重点！干货分享：经营者集中申报标准的调整及其影响</p>"
    },
    {
      "id": "a442a0fd3017",
      "title": "同样是CRS，香港VS新加坡差在哪呢？",
      "summary": "新加坡账户如何规避CRS？答案是....",
      "source": "B站",
      "platform_class": "platform-bilibili",
      "author": "Amanda跨境说",
      "url": "http://www.bilibili.com/video/av116023357347508",
      "time": "2026-05-09 10:29",
      "heat": 52,
      "discussions": "0",
      "tags": [],
      "isHot": false,
      "detail": "<p>新加坡账户如何规避CRS？答案是....</p>"
    },
    {
      "id": "1f9717533c43",
      "title": "外管证的开具及涉税流程",
      "summary": "-",
      "source": "B站",
      "platform_class": "platform-bilibili",
      "author": "bili_12743035630",
      "url": "http://www.bilibili.com/video/av115257091558595",
      "time": "2026-05-09 10:29",
      "heat": 51,
      "discussions": "1",
      "tags": [],
      "isHot": false,
      "detail": "<p>-</p>"
    },
    {
      "id": "73442e4405bc",
      "title": "如何界定“中国税务居民”身份，讲透讲清楚",
      "summary": "我们正处在一个新的时代：\n 全球税务透明、全球大数据协同的时代。\n过去是：\n “我不说，你不知道。”\n 现在是：\n “你以为国家不知道？国家都在等你主动申报。”\n所以，记住三件事：\n① 先判断你是不是中国税务居民\n ② 海外收入必须申报\n ③ 税务规划要提前，而不是被动补税\n全球征税时代已经到来，\n 你属于哪个国家的税务居民，比你赚多少钱，更重要。",
      "source": "B站",
      "platform_class": "platform-bilibili",
      "author": "无忧启程移民",
      "url": "http://www.bilibili.com/video/av115512944105575",
      "time": "2026-05-09 10:29",
      "heat": 44,
      "discussions": "1",
      "tags": [],
      "isHot": false,
      "detail": "<p>我们正处在一个新的时代：\n 全球税务透明、全球大数据协同的时代。\n过去是：\n “我不说，你不知道。”\n 现在是：\n “你以为国家不知道？国家都在等你主动申报。”\n所以，记住三件事：\n① 先判断你是不是中国税务居民\n ② 海外收入必须申报\n ③ 税务规划要提前，而不是被动补税\n全球征税时代已经到来，\n 你属于哪个国家的税务居民，比你赚多少钱，更重要。</p>"
    },
    {
      "id": "ffa6eb22b891",
      "title": "确定！ebay互联网销售涉税信息数据会申报",
      "summary": "确定！ebay互联网销售涉税信息数据会申报",
      "source": "B站",
      "platform_class": "platform-bilibili",
      "author": "源仙声的不得不小号",
      "url": "http://www.bilibili.com/video/av115359885631275",
      "time": "2026-05-09 10:29",
      "heat": 38,
      "discussions": "0",
      "tags": [],
      "isHot": false,
      "detail": "<p>确定！ebay互联网销售涉税信息数据会申报</p>"
    },
    {
      "id": "5218f60a1a7f",
      "title": "微店、视频号、小红书、闲鱼、快手获取涉税信息数据方法",
      "summary": "-",
      "source": "B站",
      "platform_class": "platform-bilibili",
      "author": "罗老师财税",
      "url": "http://www.bilibili.com/video/av115389178642670",
      "time": "2026-05-09 10:29",
      "heat": 22,
      "discussions": "0",
      "tags": [],
      "isHot": false,
      "detail": "<p>-</p>"
    },
    {
      "id": "51a8cc3af684",
      "title": "CRS2.0时代税务穿透式监管！投资港美股使用马来西亚TIN税号搭配盈立新加坡证券帐户更改税务身份的申报归属其实不靠谱，银行仍然会交换帐户信息！一个视频讲清楚",
      "summary": "-海外券商港美股远程开户\n盈立新加坡：\n邀请码：n759q9\nusmart.sg/?HCode=n759q9\n\nWealth Broker华通玖安：\n邀请码：U604M\np.wbroker.info/Hra0Dk7?lan=en",
      "source": "B站",
      "platform_class": "platform-bilibili",
      "author": "爱打劫的警长",
      "url": "http://www.bilibili.com/video/av116453390943969",
      "time": "2026-05-09 10:29",
      "heat": 13,
      "discussions": "0",
      "tags": [],
      "isHot": false,
      "detail": "<p>-海外券商港美股远程开户\n盈立新加坡：\n邀请码：n759q9\nusmart.sg/?HCode=n759q9\n\nWealth Broker华通玖安：\n邀请码：U604M\np.wbroker.info/Hra0Dk7?lan=en</p>"
    },
    {
      "id": "014fb9655b0a",
      "title": "警惕！个税新规申报错一步，员工工资少拿还罚你！财务必看的减除费用大坑。#个税新规 #财税合规 #会计实操 #工资申报",
      "summary": "警惕！个税新规申报错一步，员工工资少拿还罚你！财务必看的减除费用大坑。#个税新规 #财税合规 #会计实操 #工资申报",
      "source": "B站",
      "platform_class": "platform-bilibili",
      "author": "财税老钱",
      "url": "http://www.bilibili.com/video/av116434600461336",
      "time": "2026-05-09 10:29",
      "heat": 12,
      "discussions": "0",
      "tags": [],
      "isHot": false,
      "detail": "<p>警惕！个税新规申报错一步，员工工资少拿还罚你！财务必看的减除费用大坑。#个税新规 #财税合规 #会计实操 #工资申报</p>"
    },
    {
      "id": "0eaac24fcb5c",
      "title": "823CRS课程：家族信托披露后要交税吗",
      "summary": "-",
      "source": "B站",
      "platform_class": "platform-bilibili",
      "author": "静心家族办公室",
      "url": "http://www.bilibili.com/video/av116495954740392",
      "time": "2026-05-09 10:29",
      "heat": 9,
      "discussions": "0",
      "tags": [],
      "isHot": false,
      "detail": "<p>-</p>"
    },
    {
      "id": "663310620c18",
      "title": "2026届稀土集团春招如何报名？ | 公告解读、网申报名入口、备考避坑攻略",
      "summary": "关于稀土集团2026届春招，这个视频帮你搞懂！已同步更新稀土集团备考题库，建议结合【职题库】系统化准备！\n✅招聘公告整理解读\n✅网申报名重点分析\n看完少走弯路，愿大家都能顺利上岸！@职题库",
      "source": "B站",
      "platform_class": "platform-bilibili",
      "author": "职题库",
      "url": "http://www.bilibili.com/video/av116531975490602",
      "time": "2026-05-09 10:29",
      "heat": 4,
      "discussions": "0",
      "tags": [],
      "isHot": false,
      "detail": "<p>关于稀土集团2026届春招，这个视频帮你搞懂！已同步更新稀土集团备考题库，建议结合【职题库】系统化准备！\n✅招聘公告整理解读\n✅网申报名重点分析\n看完少走弯路，愿大家都能顺利上岸！@职题库</p>"
    },
    {
      "id": "322d6614f84a",
      "title": "海关信用新政必读｜AEO认证实用手册天地纵横团队倾力编著精讲282号令新规、五级信用等级、AEO两级认证标准全流程申报+审核+整改实操指南，手把手通关拿证",
      "summary": "海关信用新政必读｜AEO认证实用手册\n天地纵横团队倾力编著\n精讲282号令新规、五级信用等级、AEO两级认证标准\n全流程申报+审核+整改实操指南，手把手通关拿证\n解锁优先通关、降查验、全球互认福利，外贸企业必备！",
      "source": "B站",
      "platform_class": "platform-bilibili",
      "author": "北京兴海图书赵佳",
      "url": "http://www.bilibili.com/video/av116541857210032",
      "time": "2026-05-09 10:29",
      "heat": 2,
      "discussions": "0",
      "tags": [],
      "isHot": false,
      "detail": "<p>海关信用新政必读｜AEO认证实用手册\n天地纵横团队倾力编著\n精讲282号令新规、五级信用等级、AEO两级认证标准\n全流程申报+审核+整改实操指南，手把手通关拿证\n解锁优先通关、降查验、全球互认福利，外贸企业必备！</p>"
    },
    {
      "id": "ae442abffed0",
      "title": "紧急提醒！3月1号起2025年境外收入申报开始，6月30号截止，超过就收滞纳金！#境外收入申报 #税务申报 #CRS #税务合规",
      "summary": "-",
      "source": "B站",
      "platform_class": "platform-bilibili",
      "author": "小卡的港知识",
      "url": "http://www.bilibili.com/video/av116129238353596",
      "time": "2026-05-09 10:29",
      "heat": 2,
      "discussions": "0",
      "tags": [],
      "isHot": false,
      "detail": "<p>-</p>"
    }
  ]
}