{
  "updated_at": "2026-05-20T20:21:15.859053+08:00",
  "count": 59,
  "topics": [
    {
      "id": "85fb3d48699e",
      "title": "新版电子税务局，小规模零申报操作流程",
      "summary": "-",
      "source": "B站",
      "platform_class": "platform-bilibili",
      "author": "百合财税",
      "url": "http://www.bilibili.com/video/av1456007058",
      "time": "2026-05-20 20:21",
      "heat": 7472,
      "discussions": "218",
      "tags": [],
      "isHot": true,
      "detail": "<p>-</p>"
    },
    {
      "id": "2b192ce20290",
      "title": "全球征税时代到来",
      "summary": "全球征税时代到来",
      "source": "B站",
      "platform_class": "platform-bilibili",
      "author": "EverEstate",
      "url": "http://www.bilibili.com/video/av115983377238843",
      "time": "2026-05-20 20:21",
      "heat": 7430,
      "discussions": "360",
      "tags": [
        "全球征税"
      ],
      "isHot": true,
      "detail": "<p>全球征税时代到来</p>"
    },
    {
      "id": "73a95a1ad689",
      "title": "为什么现在才开始大范围的CRS交换，境外收入补税？【David.D】",
      "summary": "为什么现在才开始大范围的CRS交换，境外收入补税？【David.D】",
      "source": "B站",
      "platform_class": "platform-bilibili",
      "author": "David邓博士金融学长",
      "url": "http://www.bilibili.com/video/av114901347472563",
      "time": "2026-05-20 20:21",
      "heat": 6590,
      "discussions": "237",
      "tags": [],
      "isHot": true,
      "detail": "<p>为什么现在才开始大范围的CRS交换，境外收入补税？【David.D】</p>"
    },
    {
      "id": "c96c0bf7d96a",
      "title": "非标没了！信托公司要往哪走？——信托三分类（一）",
      "summary": "非标没了！信托公司要往哪走？——信托三分类（一）",
      "source": "B站",
      "platform_class": "platform-bilibili",
      "author": "信托徐Sir",
      "url": "http://www.bilibili.com/video/av995491938",
      "time": "2026-05-20 20:21",
      "heat": 6158,
      "discussions": "121",
      "tags": [],
      "isHot": false,
      "detail": "<p>非标没了！信托公司要往哪走？——信托三分类（一）</p>"
    },
    {
      "id": "c4d3371b4d0e",
      "title": "个体工商户如何申报纳税",
      "summary": "查账征收的个体户主要就申报增值税和经营所得税，增值税有一个季度30万的免税额度，经营所得也有一年6万的免税额度，不要忘记享受？",
      "source": "B站",
      "platform_class": "platform-bilibili",
      "author": "会计收徒丶信德",
      "url": "http://www.bilibili.com/video/av115863722202805",
      "time": "2026-05-20 20:21",
      "heat": 5522,
      "discussions": "100",
      "tags": [],
      "isHot": false,
      "detail": "<p>查账征收的个体户主要就申报增值税和经营所得税，增值税有一个季度30万的免税额度，经营所得也有一年6万的免税额度，不要忘记享受？</p>"
    },
    {
      "id": "e3273c15b705",
      "title": "税务会计【全54讲】【含资料】【中南财经政法大学】【国家级精品课】",
      "summary": "参考教材：税务会计学 作者：郭月梅 出版社：西安交通大学出版社 出版月份：2018-02\n税收会计是一门综合应用性很强的学科，它以财务会计和税法为基础，是同时如合并重组中的税务问题又和财务管理、金融学、投资学、法学等学科相联系。因此，通过本课程的学习，学生应获得以下基本技能：将税法知识与会计处理对应，掌握纳税过程从纳税义务产生、缴纳税务、申报退税等环节的会计处理；重点掌握会计准则与所得税法的区别，",
      "source": "B站",
      "platform_class": "platform-bilibili",
      "author": "爱学习的小刚子",
      "url": "http://www.bilibili.com/video/av115073011946776",
      "time": "2026-05-20 20:21",
      "heat": 3864,
      "discussions": "10",
      "tags": [],
      "isHot": false,
      "detail": "<p>参考教材：税务会计学 作者：郭月梅 出版社：西安交通大学出版社 出版月份：2018-02\n税收会计是一门综合应用性很强的学科，它以财务会计和税法为基础，是同时如合并重组中的税务问题又和财务管理、金融学、投资学、法学等学科相联系。因此，通过本课程的学习，学生应获得以下基本技能：将税法知识与会计处理对应，掌握纳税过程从纳税义务产生、缴纳税务、申报退税等环节的会计处理；重点掌握会计准则与所得税法的区别，</p>"
    },
    {
      "id": "475b2d1919bf",
      "title": "震撼所有富人的海外信托",
      "summary": "震撼所有富人的海外信托",
      "source": "B站",
      "platform_class": "platform-bilibili",
      "author": "源哥谈商",
      "url": "http://www.bilibili.com/video/av994222460",
      "time": "2026-05-20 20:21",
      "heat": 3853,
      "discussions": "23",
      "tags": [
        "海外信托"
      ],
      "isHot": false,
      "detail": "<p>震撼所有富人的海外信托</p>"
    },
    {
      "id": "8257b0b35fb4",
      "title": "2025年新版电子税务局税务注销全流程",
      "summary": "-",
      "source": "B站",
      "platform_class": "platform-bilibili",
      "author": "晗妈会计",
      "url": "http://www.bilibili.com/video/av114640730195595",
      "time": "2026-05-20 20:21",
      "heat": 3376,
      "discussions": "128",
      "tags": [],
      "isHot": false,
      "detail": "<p>-</p>"
    },
    {
      "id": "456a46cbd66e",
      "title": "【第242期】《全球征税实属被熊猫所逼》",
      "summary": "【第242期】《全球征税实属被熊猫所逼》",
      "source": "B站",
      "platform_class": "platform-bilibili",
      "author": "听风的蝉__",
      "url": "http://www.bilibili.com/video/av114325318534521",
      "time": "2026-05-20 20:21",
      "heat": 2625,
      "discussions": "20",
      "tags": [
        "全球征税"
      ],
      "isHot": false,
      "detail": "<p>【第242期】《全球征税实属被熊猫所逼》</p>"
    },
    {
      "id": "c35b5fe65e26",
      "title": "5月工信部申报比亚迪海狮08申报完毕，配置信息详细解读，内饰设计参考！价格估计10，闪充+超长续航！",
      "summary": "-",
      "source": "B站",
      "platform_class": "platform-bilibili",
      "author": "比亚迪-健总AUTO",
      "url": "http://www.bilibili.com/video/av116549037987840",
      "time": "2026-05-20 20:21",
      "heat": 1731,
      "discussions": "95",
      "tags": [],
      "isHot": false,
      "detail": "<p>-</p>"
    },
    {
      "id": "fc9bc1887235",
      "title": "车辆购置税申报缴纳实操",
      "summary": "车辆购置税申报缴纳实操。\n#财税 #知识分享 #车辆购置税 #纳税申报 #税收优惠",
      "source": "B站",
      "platform_class": "platform-bilibili",
      "author": "财税人说财税事",
      "url": "http://www.bilibili.com/video/av114625244828905",
      "time": "2026-05-20 20:21",
      "heat": 1121,
      "discussions": "32",
      "tags": [],
      "isHot": false,
      "detail": "<p>车辆购置税申报缴纳实操。\n#财税 #知识分享 #车辆购置税 #纳税申报 #税收优惠</p>"
    },
    {
      "id": "399332c051f8",
      "title": "PropFirm 收入与税务申报",
      "summary": "下半年很多人都遇到的补税情况，了解清楚，不罚款。",
      "source": "B站",
      "platform_class": "platform-bilibili",
      "author": "昵称被注册的-小水果",
      "url": "http://www.bilibili.com/video/av115705143889829",
      "time": "2026-05-20 20:21",
      "heat": 1079,
      "discussions": "111",
      "tags": [],
      "isHot": false,
      "detail": "<p>下半年很多人都遇到的补税情况，了解清楚，不罚款。</p>"
    },
    {
      "id": "b3330fdc3337",
      "title": "「影刀RPA」 财务机器人：税务局自动纳税申报",
      "summary": "如需在企业里使用该自动化应用，填写申请：https://ying-dao.feishu.cn/share/base/form/shrcnhAcnPkKTixfcWiVjqQ2uFh\n加入RPA学习群：https://mp.weixin.qq.com/s/5BLHkJq6Tk4Z-XxLtsjXOw",
      "source": "B站",
      "platform_class": "platform-bilibili",
      "author": "影刀RPA",
      "url": "http://www.bilibili.com/video/av647824949",
      "time": "2026-05-20 20:21",
      "heat": 955,
      "discussions": "14",
      "tags": [],
      "isHot": false,
      "detail": "<p>如需在企业里使用该自动化应用，填写申请：https://ying-dao.feishu.cn/share/base/form/shrcnhAcnPkKTixfcWiVjqQ2uFh\n加入RPA学习群：https://mp.weixin.qq.com/s/5BLHkJq6Tk4Z-XxLtsjXOw</p>"
    },
    {
      "id": "dbbea7017e1c",
      "title": "CRS全球金融资产征税，门槛金额和交换标准，合法规避CRS的方法",
      "summary": "CRS全球金融资产征税，门槛金额和交换标准，合法规避CRS的方法",
      "source": "B站",
      "platform_class": "platform-bilibili",
      "author": "宝儿助理",
      "url": "http://www.bilibili.com/video/av114792882902695",
      "time": "2026-05-20 20:21",
      "heat": 910,
      "discussions": "26",
      "tags": [],
      "isHot": false,
      "detail": "<p>CRS全球金融资产征税，门槛金额和交换标准，合法规避CRS的方法</p>"
    },
    {
      "id": "55518c507a9a",
      "title": "会计：一次性年终奖金在个税系统如何申报",
      "summary": "一次性年终奖，自然人电子税务局，个人所得税\n一次性年终奖，自然人电子税务局，个人所得税",
      "source": "B站",
      "platform_class": "platform-bilibili",
      "author": "是语冰吖",
      "url": "http://www.bilibili.com/video/av354236082",
      "time": "2026-05-20 20:21",
      "heat": 682,
      "discussions": "9",
      "tags": [],
      "isHot": false,
      "detail": "<p>一次性年终奖，自然人电子税务局，个人所得税\n一次性年终奖，自然人电子税务局，个人所得税</p>"
    },
    {
      "id": "b4e45f3a7902",
      "title": "申报个税时，提示“上一属期按照6万扣除累计减除费用，请继续保持或从1月属期开始更正“怎么办？",
      "summary": "申报个税时，提示“上一属期按照6万扣除累计减除费用，请继续保持或从1月属期开始更正“怎么办？",
      "source": "B站",
      "platform_class": "platform-bilibili",
      "author": "会计实操谦谦老师",
      "url": "http://www.bilibili.com/video/av114498258077881",
      "time": "2026-05-20 20:21",
      "heat": 555,
      "discussions": "10",
      "tags": [],
      "isHot": false,
      "detail": "<p>申报个税时，提示“上一属期按照6万扣除累计减除费用，请继续保持或从1月属期开始更正“怎么办？</p>"
    },
    {
      "id": "5e6e60953b00",
      "title": "取得境外所得如何通过个税APP申报个人所得税(浙江税务)",
      "summary": "宝子们！5月29日还没报境外所得个税的注意啦！今年起用个税APP就能搞定，超省心～\n\n哪些算境外所得？像海外工资、境外股息、转让境外房产等9类收入都要报，具体看财政部2020年3号公告！记得每年3月1日-6月30日申报，现在只剩最后几天，别漏了！\n\n操作超简单：打开个税APP，首页搜“年度汇算（取得境外所得适用）”，填境内外综合所得、经营所得，利息股息等分类所得单独填；境外已缴税别慌，系统自动算抵",
      "source": "B站",
      "platform_class": "platform-bilibili",
      "author": "税务师木木",
      "url": "http://www.bilibili.com/video/av114588066516202",
      "time": "2026-05-20 20:21",
      "heat": 496,
      "discussions": "3",
      "tags": [],
      "isHot": false,
      "detail": "<p>宝子们！5月29日还没报境外所得个税的注意啦！今年起用个税APP就能搞定，超省心～\n\n哪些算境外所得？像海外工资、境外股息、转让境外房产等9类收入都要报，具体看财政部2020年3号公告！记得每年3月1日-6月30日申报，现在只剩最后几天，别漏了！\n\n操作超简单：打开个税APP，首页搜“年度汇算（取得境外所得适用）”，填境内外综合所得、经营所得，利息股息等分类所得单独填；境外已缴税别慌，系统自动算抵</p>"
    },
    {
      "id": "275e35f8bd20",
      "title": "CRS， 收到税务局通知，境外炒股，到底要补多少钱？别猜了，3分钟算清楚！｜财富种植园",
      "summary": "收到稅務局通知心慌慌？境外資產補稅到底要補多少錢？\n別再自己瞎猜了！這期視頻手把手教你：上傳月結單，AI 3 分鐘幫你算得明明白白！\n很多人最近都收到了要求「境外所得自查」的短信或電話，第一反應都是：\n「我這幾年美股/港股到底賺了多少？」\n「虧損的部分能不能扣除？」\n「稅率是多少？要怎麼寫申報材料？」\n自己算，賬單幾百頁，先進先出（FIFO）算法算到頭大；請會計，收費貴不說，資料往來還麻煩。\n本期",
      "source": "B站",
      "platform_class": "platform-bilibili",
      "author": "财富种植园",
      "url": "http://www.bilibili.com/video/av115896269932539",
      "time": "2026-05-20 20:21",
      "heat": 493,
      "discussions": "12",
      "tags": [],
      "isHot": false,
      "detail": "<p>收到稅務局通知心慌慌？境外資產補稅到底要補多少錢？\n別再自己瞎猜了！這期視頻手把手教你：上傳月結單，AI 3 分鐘幫你算得明明白白！\n很多人最近都收到了要求「境外所得自查」的短信或電話，第一反應都是：\n「我這幾年美股/港股到底賺了多少？」\n「虧損的部分能不能扣除？」\n「稅率是多少？要怎麼寫申報材料？」\n自己算，賬單幾百頁，先進先出（FIFO）算法算到頭大；請會計，收費貴不說，資料往來還麻煩。\n本期</p>"
    },
    {
      "id": "1ce39cf92fca",
      "title": "社保缴费基数和工资申报一致的通知收到了吗",
      "summary": "-",
      "source": "B站",
      "platform_class": "platform-bilibili",
      "author": "晗妈会计",
      "url": "http://www.bilibili.com/video/av116567023093497",
      "time": "2026-05-20 20:21",
      "heat": 480,
      "discussions": "13",
      "tags": [],
      "isHot": false,
      "detail": "<p>-</p>"
    },
    {
      "id": "ee77dce60a8c",
      "title": "富豪们的家族信托：信托真能合法避税吗？",
      "summary": "富豪们的家族信托：信托真能合法避税吗？\n①信托的基本知识\n②家族信托知识\n③信托税收知识",
      "source": "B站",
      "platform_class": "platform-bilibili",
      "author": "懂点税",
      "url": "http://www.bilibili.com/video/av114862491439253",
      "time": "2026-05-20 20:21",
      "heat": 473,
      "discussions": "12",
      "tags": [],
      "isHot": false,
      "detail": "<p>富豪们的家族信托：信托真能合法避税吗？\n①信托的基本知识\n②家族信托知识\n③信托税收知识</p>"
    },
    {
      "id": "1be245cc708d",
      "title": "护士如何完成自己的三新技术与课题的申报？",
      "summary": "什么是护理新技术和护理课题？如何完成新技术和课题的申报？一文告诉你！",
      "source": "B站",
      "platform_class": "platform-bilibili",
      "author": "无影师弟",
      "url": "http://www.bilibili.com/video/av114550133231203",
      "time": "2026-05-20 20:21",
      "heat": 333,
      "discussions": "3",
      "tags": [],
      "isHot": false,
      "detail": "<p>什么是护理新技术和护理课题？如何完成新技术和课题的申报？一文告诉你！</p>"
    },
    {
      "id": "9b3b3b0c0e78",
      "title": "CRS: 2026 境外投資稅務申報教學：AI 自動計算美股/港股投資所得，個人所得稅 APP 報稅全攻略",
      "summary": "💡 境外投資報稅太複雜？請會計太貴？本視頻手把手教你使用最新的 AI 稅務工具，自動化處理你的券商月報表、年報表，一鍵生成符合審計要求的 Excel 底稿，讓你在個人所得稅 APP 申報時輕鬆無憂！\n\n📌 視頻核心內容：\n00:00 工具背景與核心價值（省時、省錢、防風險）\n01:08 免費體驗額度獲取與定價方案\n02:00 邀請碼機制：雙方均可獲得 50% 額外額度\n02:40 數據安全保障：本",
      "source": "B站",
      "platform_class": "platform-bilibili",
      "author": "财富种植园",
      "url": "http://www.bilibili.com/video/av116132493133650",
      "time": "2026-05-20 20:21",
      "heat": 260,
      "discussions": "15",
      "tags": [],
      "isHot": false,
      "detail": "<p>💡 境外投資報稅太複雜？請會計太貴？本視頻手把手教你使用最新的 AI 稅務工具，自動化處理你的券商月報表、年報表，一鍵生成符合審計要求的 Excel 底稿，讓你在個人所得稅 APP 申報時輕鬆無憂！\n\n📌 視頻核心內容：\n00:00 工具背景與核心價值（省時、省錢、防風險）\n01:08 免費體驗額度獲取與定價方案\n02:00 邀請碼機制：雙方均可獲得 50% 額外額度\n02:40 數據安全保障：本</p>"
    },
    {
      "id": "6f52948d7a53",
      "title": "【完全搞懂VAT！】欧洲跨境必修课：注册+申报+缴税，一次讲透！连平台代缴功能都教你怎么用！新卖家也能看懂",
      "summary": "这期视频我会用3分钟的结构，带你快速搞懂VAT注册 + 申报 + 缴税的核心流程，\n还会告诉你哪些平台支持免费代缴，怎么操作最省心，一看就懂，少走很多弯路。\n\n✅ 视频对应图文文章：\nhttps://mp.weixin.qq.com/s/Pl0U1pQcJoc5Fs8C4sQZ2Q",
      "source": "B站",
      "platform_class": "platform-bilibili",
      "author": "136F跨境小贴士",
      "url": "http://www.bilibili.com/video/av115434762469798",
      "time": "2026-05-20 20:21",
      "heat": 243,
      "discussions": "6",
      "tags": [],
      "isHot": false,
      "detail": "<p>这期视频我会用3分钟的结构，带你快速搞懂VAT注册 + 申报 + 缴税的核心流程，\n还会告诉你哪些平台支持免费代缴，怎么操作最省心，一看就懂，少走很多弯路。\n\n✅ 视频对应图文文章：\nhttps://mp.weixin.qq.com/s/Pl0U1pQcJoc5Fs8C4sQZ2Q</p>"
    },
    {
      "id": "1a4906145af4",
      "title": "湾区渣男5-信托财富博弈背后的深度宅斗",
      "summary": "-",
      "source": "B站",
      "platform_class": "platform-bilibili",
      "author": "狗驲的虎扑",
      "url": "http://www.bilibili.com/video/av114147916255938",
      "time": "2026-05-20 20:21",
      "heat": 242,
      "discussions": "16",
      "tags": [],
      "isHot": false,
      "detail": "<p>-</p>"
    },
    {
      "id": "923c9bcb2d25",
      "title": "中国开启全球征税时代！境外收入恶意逃税可能要坐牢",
      "summary": "中国税务居民在海外赚了钱，都需要向中国税务机关报税。如果不报税被查出来，则将面临补税+罚款，恶意逃税者还将承担刑事责任，牢饭供应。\n \n本来境外收入报税交税这件事，喊了很多年，但因为技术原因并未普及开来。但是现在，技术的进步与国际合作的紧密，让心存侥幸者无所遁形。\n \n近日，中国的浙江、山东、上海、湖北四地税务机关同步发布公告，针对中国境内居民的境外收入申报问题开展集中核查。\n \n通过大数据识别出",
      "source": "B站",
      "platform_class": "platform-bilibili",
      "author": "无忧启程移民",
      "url": "http://www.bilibili.com/video/av114420143494580",
      "time": "2026-05-20 20:21",
      "heat": 198,
      "discussions": "8",
      "tags": [
        "全球征税"
      ],
      "isHot": false,
      "detail": "<p>中国税务居民在海外赚了钱，都需要向中国税务机关报税。如果不报税被查出来，则将面临补税+罚款，恶意逃税者还将承担刑事责任，牢饭供应。\n \n本来境外收入报税交税这件事，喊了很多年，但因为技术原因并未普及开来。但是现在，技术的进步与国际合作的紧密，让心存侥幸者无所遁形。\n \n近日，中国的浙江、山东、上海、湖北四地税务机关同步发布公告，针对中国境内居民的境外收入申报问题开展集中核查。\n \n通过大数据识别出</p>"
    },
    {
      "id": "c0123dc6b505",
      "title": "分公司都需要申报哪些税零申报全流程",
      "summary": "-",
      "source": "B站",
      "platform_class": "platform-bilibili",
      "author": "晗妈会计",
      "url": "http://www.bilibili.com/video/av114822914050754",
      "time": "2026-05-20 20:21",
      "heat": 178,
      "discussions": "1",
      "tags": [],
      "isHot": false,
      "detail": "<p>-</p>"
    },
    {
      "id": "e521de0c3fdb",
      "title": "今天来教大家如何境外收入交税。",
      "summary": "今天来教大家如何境外收入交税。‌\n#境外收入 #海外投资 #全球征税 #纳税 #个人所得税",
      "source": "B站",
      "platform_class": "platform-bilibili",
      "author": "阮诗赋",
      "url": "http://www.bilibili.com/video/av115071871096063",
      "time": "2026-05-20 20:21",
      "heat": 145,
      "discussions": "5",
      "tags": [
        "全球征税"
      ],
      "isHot": false,
      "detail": "<p>今天来教大家如何境外收入交税。‌\n#境外收入 #海外投资 #全球征税 #纳税 #个人所得税</p>"
    },
    {
      "id": "cdaf0da16f01",
      "title": "【1/3】家族信托、家庭信托、保险金信托介绍",
      "summary": "茫茫尘世中一个伴读小书童，温酒与你共同成长~",
      "source": "B站",
      "platform_class": "platform-bilibili",
      "author": "温酒醉琉璃",
      "url": "http://www.bilibili.com/video/av1202068801",
      "time": "2026-05-20 20:21",
      "heat": 114,
      "discussions": "4",
      "tags": [],
      "isHot": false,
      "detail": "<p>茫茫尘世中一个伴读小书童，温酒与你共同成长~</p>"
    },
    {
      "id": "d8fa56c29a87",
      "title": "长安信托现“内鬼”，“阴阳合同”瞒天过海",
      "summary": "长安信托现“内鬼”，“阴阳合同”瞒天过海",
      "source": "B站",
      "platform_class": "platform-bilibili",
      "author": "冯博内控财务正经谈",
      "url": "http://www.bilibili.com/video/av210175304",
      "time": "2026-05-20 20:21",
      "heat": 108,
      "discussions": "2",
      "tags": [],
      "isHot": false,
      "detail": "<p>长安信托现“内鬼”，“阴阳合同”瞒天过海</p>"
    },
    {
      "id": "180b1c3c1059",
      "title": "谁是CRS全球征税最最最危险的？最容易暴雷的是哪些群体？陈震、薇娅他们是如何翻车的？",
      "summary": "谁是CRS全球征税最最最危险的？最容易暴雷的是哪些群体？陈震、薇娅他们是如何翻车的？",
      "source": "B站",
      "platform_class": "platform-bilibili",
      "author": "WilliamLC移民",
      "url": "http://www.bilibili.com/video/av116471443229215",
      "time": "2026-05-20 20:21",
      "heat": 104,
      "discussions": "8",
      "tags": [
        "全球征税"
      ],
      "isHot": false,
      "detail": "<p>谁是CRS全球征税最最最危险的？最容易暴雷的是哪些群体？陈震、薇娅他们是如何翻车的？</p>"
    },
    {
      "id": "565780d22a57",
      "title": "内地信托vs香港信托，三个区别惊呆你！",
      "summary": "对于很多高净值人士来说，在海外进行资产配置是非常有必要，重新开关一年的香港，也是大多数人离岸配置的第一站。\n\n在的财富逐渐积累的情况下，不管内地还是离岸，信托一定是富豪们热衷的选择之一。和内地独具特色会暴雷的信托理财不同的是，在欧美国家和香港等地，信托其实就只是一种财富传承和遗产规划的法律工具而已。\n\n那今天给大家科普一下国内信托和香港的信托的是三个不同区别。",
      "source": "B站",
      "platform_class": "platform-bilibili",
      "author": "托雷教你避雷",
      "url": "http://www.bilibili.com/video/av1752965688",
      "time": "2026-05-20 20:21",
      "heat": 94,
      "discussions": "1",
      "tags": [],
      "isHot": false,
      "detail": "<p>对于很多高净值人士来说，在海外进行资产配置是非常有必要，重新开关一年的香港，也是大多数人离岸配置的第一站。\n\n在的财富逐渐积累的情况下，不管内地还是离岸，信托一定是富豪们热衷的选择之一。和内地独具特色会暴雷的信托理财不同的是，在欧美国家和香港等地，信托其实就只是一种财富传承和遗产规划的法律工具而已。\n\n那今天给大家科普一下国内信托和香港的信托的是三个不同区别。</p>"
    },
    {
      "id": "d073c1204fdb",
      "title": "谁说印尼税轻？你挨过VAT、预扣、分红组合拳吗？",
      "summary": "在印尼做企业，难点从来不在“税率高不高”，而是——你根本没算清真实税负和钱能不能回到母公司。\n\n本期视频 20 分钟带你看懂印尼整套税务逻辑：\n22% 企业所得税 + 11% 增值税 + 10–20% 预扣税，叠加后的“真实税负”到底有多高？\n非居民收款、管理费、特许权使用费，为什么总是在合同签完后才发现被多扣了 20%？\n双重征税协定什么时候真能把税率从 20% 拉到 5–10%，e-备案和居民",
      "source": "B站",
      "platform_class": "platform-bilibili",
      "author": "万企帮集团",
      "url": "http://www.bilibili.com/video/av115631810744683",
      "time": "2026-05-20 20:21",
      "heat": 93,
      "discussions": "4",
      "tags": [],
      "isHot": false,
      "detail": "<p>在印尼做企业，难点从来不在“税率高不高”，而是——你根本没算清真实税负和钱能不能回到母公司。\n\n本期视频 20 分钟带你看懂印尼整套税务逻辑：\n22% 企业所得税 + 11% 增值税 + 10–20% 预扣税，叠加后的“真实税负”到底有多高？\n非居民收款、管理费、特许权使用费，为什么总是在合同签完后才发现被多扣了 20%？\n双重征税协定什么时候真能把税率从 20% 拉到 5–10%，e-备案和居民</p>"
    },
    {
      "id": "0e8e2fa17e4b",
      "title": "《如何利用海外家族信托做好财富传承》",
      "summary": "《如何利用海外家族信托做好财富传承》",
      "source": "B站",
      "platform_class": "platform-bilibili",
      "author": "侨外出国",
      "url": "http://www.bilibili.com/video/av947063286",
      "time": "2026-05-20 20:21",
      "heat": 88,
      "discussions": "1",
      "tags": [],
      "isHot": false,
      "detail": "<p>《如何利用海外家族信托做好财富传承》</p>"
    },
    {
      "id": "300dbec0e1d4",
      "title": "在中国法院起诉离婚，可以分割境外资产吗？",
      "summary": "在中国法院起诉离婚，可以分割境外资产吗？",
      "source": "B站",
      "platform_class": "platform-bilibili",
      "author": "张亚敏律师",
      "url": "http://www.bilibili.com/video/av113526018611756",
      "time": "2026-05-20 20:21",
      "heat": 87,
      "discussions": "1",
      "tags": [],
      "isHot": false,
      "detail": "<p>在中国法院起诉离婚，可以分割境外资产吗？</p>"
    },
    {
      "id": "4d5d678ff878",
      "title": "什么是信托通道业务？如何核实信托产品的真实性？",
      "summary": "-",
      "source": "B站",
      "platform_class": "platform-bilibili",
      "author": "刘sir聊信托",
      "url": "http://www.bilibili.com/video/av701706157",
      "time": "2026-05-20 20:21",
      "heat": 85,
      "discussions": "0",
      "tags": [],
      "isHot": false,
      "detail": "<p>-</p>"
    },
    {
      "id": "8047b25a3460",
      "title": "海外资产申报 - 加拿大非税务居民的利与弊",
      "summary": "如果您的大部分收入来自海外，应该如何定义自己的居民身份呢？\n本期将为您深度解析加拿大非税务局民的利与弊。\n在什么情况下您可以被定义为非税务局民？\n只有非税务局民才能不申报海外资产你知道吗？\n非税务局民有什么弊端呢",
      "source": "B站",
      "platform_class": "platform-bilibili",
      "author": "诚信理财金融频道",
      "url": "http://www.bilibili.com/video/av800072813",
      "time": "2026-05-20 20:21",
      "heat": 67,
      "discussions": "1",
      "tags": [
        "海外资产申报"
      ],
      "isHot": false,
      "detail": "<p>如果您的大部分收入来自海外，应该如何定义自己的居民身份呢？\n本期将为您深度解析加拿大非税务局民的利与弊。\n在什么情况下您可以被定义为非税务局民？\n只有非税务局民才能不申报海外资产你知道吗？\n非税务局民有什么弊端呢</p>"
    },
    {
      "id": "ce1d57fc633d",
      "title": "【广告】中国信托uniopen联名卡",
      "summary": "伟啊fai么哩——",
      "source": "B站",
      "platform_class": "platform-bilibili",
      "author": "宝岛广告网",
      "url": "http://www.bilibili.com/video/av115086819595364",
      "time": "2026-05-20 20:21",
      "heat": 50,
      "discussions": "3",
      "tags": [],
      "isHot": false,
      "detail": "<p>伟啊fai么哩——</p>"
    },
    {
      "id": "23c36b4011ad",
      "title": "罕见！资产来自境外收购，IPO注册通过",
      "summary": "罕见！资产来自境外收购，IPO注册通过",
      "source": "B站",
      "platform_class": "platform-bilibili",
      "author": "塘主聊上市",
      "url": "http://www.bilibili.com/video/av114245609985294",
      "time": "2026-05-20 20:21",
      "heat": 42,
      "discussions": "0",
      "tags": [],
      "isHot": false,
      "detail": "<p>罕见！资产来自境外收购，IPO注册通过</p>"
    },
    {
      "id": "a7cb298c7c25",
      "title": "香港信托和内地信托有什么区别?委托人会承担什么风险?",
      "summary": "香港信托和内地信托有什么区别?委托人会承担什么风险?",
      "source": "B站",
      "platform_class": "platform-bilibili",
      "author": "小龙哥说基金",
      "url": "http://www.bilibili.com/video/av1402468848",
      "time": "2026-05-20 20:21",
      "heat": 42,
      "discussions": "1",
      "tags": [],
      "isHot": false,
      "detail": "<p>香港信托和内地信托有什么区别?委托人会承担什么风险?</p>"
    },
    {
      "id": "5df38ce2c2ce",
      "title": "境外国资工作局成立，释放什么信号？",
      "summary": "2026年4月8日国资委成立境外国资工作局，这背后，究竟藏着国家怎样的战略深意？是简单的机构调整，还是一场关乎万亿国资安全的“保卫战”？",
      "source": "B站",
      "platform_class": "platform-bilibili",
      "author": "国企改革明律师",
      "url": "http://www.bilibili.com/video/av116369538419474",
      "time": "2026-05-20 20:21",
      "heat": 40,
      "discussions": "0",
      "tags": [],
      "isHot": false,
      "detail": "<p>2026年4月8日国资委成立境外国资工作局，这背后，究竟藏着国家怎样的战略深意？是简单的机构调整，还是一场关乎万亿国资安全的“保卫战”？</p>"
    },
    {
      "id": "af95a3c1036f",
      "title": "日本境外的资产，高净值家庭可以避开55%的继承税？#信托 #信托伽 #财富架构 #风险隔离 #家族信托 #继承 #税务",
      "summary": "-",
      "source": "B站",
      "platform_class": "platform-bilibili",
      "author": "聊点海外",
      "url": "http://www.bilibili.com/video/av114935304556118",
      "time": "2026-05-20 20:21",
      "heat": 31,
      "discussions": "0",
      "tags": [],
      "isHot": false,
      "detail": "<p>-</p>"
    },
    {
      "id": "4fdbfb8c0241",
      "title": "CRS时代境外资产收入申报",
      "summary": "CRS时代境外资产收入申报\r#CRS #境外收入 #个税申报 #合规纳税 #加密资产 #跨境税务",
      "source": "B站",
      "platform_class": "platform-bilibili",
      "author": "创意保",
      "url": "http://www.bilibili.com/video/av116458726104466",
      "time": "2026-05-20 20:21",
      "heat": 24,
      "discussions": "1",
      "tags": [],
      "isHot": false,
      "detail": "<p>CRS时代境外资产收入申报\r#CRS #境外收入 #个税申报 #合规纳税 #加密资产 #跨境税务</p>"
    },
    {
      "id": "0eb8fef117fc",
      "title": "普通人也能试试的海外问卷项目，收益比想象中高",
      "summary": "-",
      "source": "B站",
      "platform_class": "platform-bilibili",
      "author": "LunarCove倾城",
      "url": "http://www.bilibili.com/video/av116600057367168",
      "time": "2026-05-20 20:21",
      "heat": 22,
      "discussions": "2",
      "tags": [],
      "isHot": false,
      "detail": "<p>-</p>"
    },
    {
      "id": "3d912c1d7ee0",
      "title": "欧洲大规模启动税务倒查，你的业务合规了吗？",
      "summary": "在寻找海外仓合作伙伴时，务必要把“资产安全”放在首位，而不是只看价格。那些真正值得信赖的海外仓服务商，往往具备一个共同特质：拥有实实在在的固定资产作为保障。",
      "source": "B站",
      "platform_class": "platform-bilibili",
      "author": "洲博通外贸综合服务",
      "url": "http://www.bilibili.com/video/av116605493184322",
      "time": "2026-05-20 20:21",
      "heat": 21,
      "discussions": "0",
      "tags": [],
      "isHot": false,
      "detail": "<p>在寻找海外仓合作伙伴时，务必要把“资产安全”放在首位，而不是只看价格。那些真正值得信赖的海外仓服务商，往往具备一个共同特质：拥有实实在在的固定资产作为保障。</p>"
    },
    {
      "id": "55b3408b7d7f",
      "title": "2026年最新，抖店商家税务申报全流程指南",
      "summary": "2026年最新，抖店商家税务申报全流程指南",
      "source": "B站",
      "platform_class": "platform-bilibili",
      "author": "晓涛聊电商财税",
      "url": "http://www.bilibili.com/video/av116342124452737",
      "time": "2026-05-20 20:21",
      "heat": 18,
      "discussions": "0",
      "tags": [],
      "isHot": false,
      "detail": "<p>2026年最新，抖店商家税务申报全流程指南</p>"
    },
    {
      "id": "cee8cf9e245b",
      "title": "小白也能上手的海外问卷任务，一天几十美金",
      "summary": "-",
      "source": "B站",
      "platform_class": "platform-bilibili",
      "author": "快乐暮汐推文",
      "url": "http://www.bilibili.com/video/av116605442988576",
      "time": "2026-05-20 20:21",
      "heat": 18,
      "discussions": "2",
      "tags": [],
      "isHot": false,
      "detail": "<p>-</p>"
    },
    {
      "id": "c7d8b3bb5d42",
      "title": "每天抽空做海外问卷，昨天直接搞了50美金",
      "summary": "-",
      "source": "B站",
      "platform_class": "platform-bilibili",
      "author": "小小-殷",
      "url": "http://www.bilibili.com/video/av116606801811196",
      "time": "2026-05-20 20:21",
      "heat": 16,
      "discussions": "2",
      "tags": [],
      "isHot": false,
      "detail": "<p>-</p>"
    },
    {
      "id": "bf4d3c7432c4",
      "title": "警惕境外融资骗局，香港国际资产管理有限公司利用合同条款实施诈骗",
      "summary": "-",
      "source": "B站",
      "platform_class": "platform-bilibili",
      "author": "生活度日如年",
      "url": "http://www.bilibili.com/video/av114591724018765",
      "time": "2026-05-20 20:21",
      "heat": 15,
      "discussions": "0",
      "tags": [],
      "isHot": false,
      "detail": "<p>-</p>"
    },
    {
      "id": "3706ee14529d",
      "title": "三星家族遗产税危机启示",
      "summary": "三星家族遗产税危机启示 \r#三星家族 #遗产税 #财富传承 #大额寿险 #信托架构",
      "source": "B站",
      "platform_class": "platform-bilibili",
      "author": "创意保",
      "url": "http://www.bilibili.com/video/av116605023491644",
      "time": "2026-05-20 20:21",
      "heat": 15,
      "discussions": "0",
      "tags": [],
      "isHot": false,
      "detail": "<p>三星家族遗产税危机启示 \r#三星家族 #遗产税 #财富传承 #大额寿险 #信托架构</p>"
    },
    {
      "id": "9387244e01ba",
      "title": "全球购平台会代扣代缴税？很多国家都是这样了，全球购可能吗？",
      "summary": "电商税落地平台代扣代缴？很多国家都是这样了，全球购可能吗？",
      "source": "B站",
      "platform_class": "platform-bilibili",
      "author": "跨境财税的春戈",
      "url": "http://www.bilibili.com/video/av113842285774893",
      "time": "2026-05-20 20:21",
      "heat": 13,
      "discussions": "0",
      "tags": [],
      "isHot": false,
      "detail": "<p>电商税落地平台代扣代缴？很多国家都是这样了，全球购可能吗？</p>"
    },
    {
      "id": "f00b9b23a74b",
      "title": "富豪移民只认新加坡？为啥一桥之隔，偏偏看不上马来西亚？差了整整一个时代。#海外移居#资本落户#亚太宜居#身份规划#投资去向#区位差异",
      "summary": "富豪移民只认新加坡？为啥一桥之隔，偏偏看不上马来西亚？差了整整一个时代。#海外移居#资本落户#亚太宜居#身份规划#投资去向#区位差异",
      "source": "B站",
      "platform_class": "platform-bilibili",
      "author": "环球新讯社",
      "url": "http://www.bilibili.com/video/av116597071022848",
      "time": "2026-05-20 20:21",
      "heat": 10,
      "discussions": "0",
      "tags": [],
      "isHot": false,
      "detail": "<p>富豪移民只认新加坡？为啥一桥之隔，偏偏看不上马来西亚？差了整整一个时代。#海外移居#资本落户#亚太宜居#身份规划#投资去向#区位差异</p>"
    },
    {
      "id": "ccc9675bee9f",
      "title": "海外的信托架构是怎么收费的？【海外信托科普】",
      "summary": "海外的信托架构是怎么收费的？【海外信托科普】",
      "source": "B站",
      "platform_class": "platform-bilibili",
      "author": "开元聊全球配置",
      "url": "http://www.bilibili.com/video/av116595242377010",
      "time": "2026-05-20 20:21",
      "heat": 8,
      "discussions": "0",
      "tags": [
        "海外信托"
      ],
      "isHot": false,
      "detail": "<p>海外的信托架构是怎么收费的？【海外信托科普】</p>"
    },
    {
      "id": "e6af63df8d9e",
      "title": "拿香港身份藏资产？境外资产“透明化”时代来了!CRS2.0来了，这条路彻底堵死了",
      "summary": "过去，有人拿香港身份、开离岸公司、买加密资产，觉得这些“跨境财富”在国内查不到。\n但2026年4月1日，香港CRS2.0正式进入立法阶段。",
      "source": "B站",
      "platform_class": "platform-bilibili",
      "author": "瓜哥外贸财税合规",
      "url": "http://www.bilibili.com/video/av116419299643707",
      "time": "2026-05-20 20:21",
      "heat": 7,
      "discussions": "0",
      "tags": [],
      "isHot": false,
      "detail": "<p>过去，有人拿香港身份、开离岸公司、买加密资产，觉得这些“跨境财富”在国内查不到。\n但2026年4月1日，香港CRS2.0正式进入立法阶段。</p>"
    },
    {
      "id": "b0ab7cac5386",
      "title": "还在为检验检疫申报头疼？这本2026最新手册帮你解决！全品类产品清单+编码对应申报要求，现行规定全收录，专家解读易错点，让你申报不踩坑，通关更高效！",
      "summary": "-",
      "source": "B站",
      "platform_class": "platform-bilibili",
      "author": "北京兴海图书赵佳",
      "url": "http://www.bilibili.com/video/av116604201409364",
      "time": "2026-05-20 20:21",
      "heat": 6,
      "discussions": "0",
      "tags": [],
      "isHot": false,
      "detail": "<p>-</p>"
    },
    {
      "id": "e8d5111ef52c",
      "title": "港籍热潮#香港身份规划#留学生#华侨生联考#海外资产规划",
      "summary": "-",
      "source": "B站",
      "platform_class": "platform-bilibili",
      "author": "肖萧看世界",
      "url": "http://www.bilibili.com/video/av116605543651928",
      "time": "2026-05-20 20:21",
      "heat": 3,
      "discussions": "0",
      "tags": [],
      "isHot": false,
      "detail": "<p>-</p>"
    },
    {
      "id": "ccf65599763b",
      "title": "境外资产安全",
      "summary": "境外资产安全",
      "source": "B站",
      "platform_class": "platform-bilibili",
      "author": "新马buff",
      "url": "http://www.bilibili.com/video/av115070965194751",
      "time": "2026-05-20 20:21",
      "heat": 3,
      "discussions": "0",
      "tags": [],
      "isHot": false,
      "detail": "<p>境外资产安全</p>"
    },
    {
      "id": "4b5903de7df7",
      "title": "全球税务透明升级，你的境外资产还好吗?",
      "summary": "近年来，越来越多中国居民接到税务部门关于境外资产申报的电话与提醒。这并非个案，而是全球税务透明化持续升级背景下的必然趋势。 \n本期视频将带你系统拆解： \n为什么境外资产“开始被看见” \n中国税务监管在2025年后的变化逻辑 \nCRS（共同申报准则）到底是什么？ \nCRS 2.0 与 CARF 将如何影响你的海外资产 \n哪些人群正在成为重点关注对象 \n在全球信息交换体系下，还有没有合法税务规划空间？",
      "source": "B站",
      "platform_class": "platform-bilibili",
      "author": "加晓说移民加拿大",
      "url": "http://www.bilibili.com/video/av116483724150572",
      "time": "2026-05-20 20:21",
      "heat": 3,
      "discussions": "0",
      "tags": [
        "境外资产申报"
      ],
      "isHot": false,
      "detail": "<p>近年来，越来越多中国居民接到税务部门关于境外资产申报的电话与提醒。这并非个案，而是全球税务透明化持续升级背景下的必然趋势。 \n本期视频将带你系统拆解： \n为什么境外资产“开始被看见” \n中国税务监管在2025年后的变化逻辑 \nCRS（共同申报准则）到底是什么？ \nCRS 2.0 与 CARF 将如何影响你的海外资产 \n哪些人群正在成为重点关注对象 \n在全球信息交换体系下，还有没有合法税务规划空间？</p>"
    },
    {
      "id": "a7c57f086567",
      "title": "出海实务 | RWA的合规探路者——境内资产的境外链上ABS",
      "summary": "RWA的合规探路者——境内资产的境外链上ABS",
      "source": "B站",
      "platform_class": "platform-bilibili",
      "author": "泰出海研究院",
      "url": "http://www.bilibili.com/video/av116475754975707",
      "time": "2026-05-20 20:21",
      "heat": 3,
      "discussions": "0",
      "tags": [],
      "isHot": false,
      "detail": "<p>RWA的合规探路者——境内资产的境外链上ABS</p>"
    },
    {
      "id": "e4d3737aee76",
      "title": "香港金管局：3月份外汇基金境外资产35706亿港元",
      "summary": "4月14日，香港金管局今日公布外汇基金在2026年3月底的主要分析帐目。\n在3月份，外汇基金的境外资产减少595亿港元，至35,706亿港元。\n货币基础为20,650亿港元，包括负债证明书、政府发行的流通纸币及硬币、银行体系结余，以及已发行外汇基金票据及债券。\n外汇基金对香港私营部门的债权总额为3,935亿港元。\n对外负债总额为788亿港元。",
      "source": "B站",
      "platform_class": "platform-bilibili",
      "author": "FinTV",
      "url": "http://www.bilibili.com/video/av116407740208142",
      "time": "2026-05-20 20:21",
      "heat": 1,
      "discussions": "0",
      "tags": [],
      "isHot": false,
      "detail": "<p>4月14日，香港金管局今日公布外汇基金在2026年3月底的主要分析帐目。\n在3月份，外汇基金的境外资产减少595亿港元，至35,706亿港元。\n货币基础为20,650亿港元，包括负债证明书、政府发行的流通纸币及硬币、银行体系结余，以及已发行外汇基金票据及债券。\n外汇基金对香港私营部门的债权总额为3,935亿港元。\n对外负债总额为788亿港元。</p>"
    }
  ]
}